HighdimensionalFeat/__init__.py
HighdimensionalFeat/discernibleScore.py
HighdimensionalFeat/fastFeatureSelectionDS.py
HighdimensionalFeat/increDiscernibleScore.py
HighdimensionalFeat/increFeaSltDSFilterSam.py
HighdimensionalFeat/increFeatureSelectionDS.py
HighdimensionalFeat/partition_fold.py
HighdimensionalFeat-0.1.3.dist-info/METADATA
HighdimensionalFeat-0.1.3.dist-info/WHEEL
HighdimensionalFeat-0.1.3.dist-info/top_level.txt
HighdimensionalFeat-0.1.3.dist-info/RECORD
